utilx/__init__.py
utilx/cli.py
utilx/deploy.py
utilx/mongo.py
utilx-1.9.3.dist-info/METADATA
utilx-1.9.3.dist-info/WHEEL
utilx-1.9.3.dist-info/entry_points.txt
utilx-1.9.3.dist-info/top_level.txt
utilx-1.9.3.dist-info/zip-safe
utilx-1.9.3.dist-info/RECORD
