Metadata-Version: 2.1
Name: utilx
Version: 1.9.3
Summary: Python Toolkit
Home-page: https://github.com/taogeYT/utilx
Author: yatao
Author-email: li_yatao@outlook.com
License: MIT
Platform: UNKNOWN
Classifier: License :: OSI Approved :: MIT License
Classifier: Environment :: Web Environment
Classifier: Intended Audience :: Developers
Classifier: Operating System :: OS Independent
Classifier: Topic :: Text Processing :: Indexing
Classifier: Topic :: Utilities
Classifier: Topic :: Internet
Classifier: Topic :: Software Development :: Libraries :: Python Modules
Classifier: Programming Language :: Python
Requires-Dist: plan (>=0.5)
Requires-Dist: fire
